setup.py
universal_usbtmc/__init__.py
universal_usbtmc/backend_factory.py
universal_usbtmc/exceptions.py
universal_usbtmc/instrument.py
universal_usbtmc/shell.py
universal_usbtmc.egg-info/PKG-INFO
universal_usbtmc.egg-info/SOURCES.txt
universal_usbtmc.egg-info/dependency_links.txt
universal_usbtmc.egg-info/entry_points.txt
universal_usbtmc.egg-info/top_level.txt
universal_usbtmc.egg-info/zip-safe
universal_usbtmc/backends/__init__.py
universal_usbtmc/backends/linux_kernel.py
universal_usbtmc/backends/pyserial.py
universal_usbtmc/backends/python_usbtmc.py
universal_usbtmc/backends/python_vxi11.py
universal_usbtmc/backends/tcp_socket.py