Metadata-Version: 1.1
Name: universal-usbtmc
Version: 0.3.3
Summary: 
Home-page: https://github.com/pklaus/universal_usbtmc
Author: Philipp Klaus
Author-email: philipp.l.klaus@web.de
License: GPL
Keywords: USBTMC
Platform: any
Classifier: Development Status :: 4 - Beta
Classifier: Operating System :: OS Independent
Classifier: License :: OSI Approved :: GNU General Public License v3 or later (GPLv3+)
Classifier: Programming Language :: Python
Classifier: Programming Language :: Python :: 2
Classifier: Programming Language :: Python :: 3
Classifier: Topic :: System :: Monitoring
Classifier: Topic :: System :: Logging
